{
  "storeVersion" : 0,
  "docType" : "Note",
  "docTypeVersion" : 5,
  "docId" : "HUSECOXXXXXXU1015",
  "content" : {
    "domain" : "ECONOMICS",
    "privateComment" : null,
    "tags" : "",
    "transpositions" : [ {
      "lang" : "FR",
      "title" : "Agrégats de production",
      "description" : "...",
      "voice" : "fr-FR-Chirp3-HD-Puck",
      "text" : "^un agrégat // {\"headword\":\"agrégat\",\"category\":\"noun\",\"gender\":\"masculine\",\"cefrLevel\":\"C1\"}\n^une production // {\"headword\":\"production\",\"category\":\"noun\",\"gender\":\"feminine\",\"cefrLevel\":\"B1\"}\n# Agrégats de production\n\n^une mesure // {\"headword\":\"mesure\",\"category\":\"noun\",\"gender\":\"feminine\",\"cefrLevel\":\"B1\"}\n## Mesure de la production\n\n^marchand // {\"headword\":\"marchand\",\"category\":\"adjective\",\"cefrLevel\":\"B1\"}\n?~ **Agrégat** mesurant la **production marchande** :\n^une valeur ajoutée // {\"headword\":\"valeur ajoutée\",\"category\":\"noun\",\"gender\":\"feminine\",\"cefrLevel\":\"B2\"}\n^c'est-à-dire // {\"headword\":\"c'est-à-dire\",\"category\":\"other\",\"cefrLevel\":\"B1\"}\n- la **valeur ajoutée**, c'est à dire :\n^un chiffre d'affaires // {\"headword\":\"chiffre d'affaires\",\"category\":\"noun\",\"gender\":\"masculine\",\"cefrLevel\":\"B2\"}\n- le **chiffre d'affaires**\n^moins // {\"headword\":\"moins\",\"category\":\"other\",\"cefrLevel\":\"A1\"}\n^une consommation // {\"headword\":\"consommation\",\"category\":\"noun\",\"gender\":\"feminine\",\"cefrLevel\":\"B1\"}\n^intermédiaire // {\"headword\":\"intermédiaire\",\"category\":\"adjective\",\"cefrLevel\":\"B1\"}\n- **moins la consommation intermédiaire**.\n\n^une estimation // {\"headword\":\"estimation\",\"category\":\"noun\",\"gender\":\"feminine\",\"cefrLevel\":\"B1\"}\n^non marchande // {\"headword\":\"non marchande\",\"category\":\"adjective\",\"cefrLevel\":\"B2\"}\n?~ **Estimation** de la **production non marchande** :\n^un coût // {\"headword\":\"coût\",\"category\":\"noun\",\"gender\":\"masculine\",\"cefrLevel\":\"B1\"}\n^un facteur de production // {\"headword\":\"facteur de production\",\"category\":\"noun\",\"gender\":\"masculine\",\"cefrLevel\":\"B2\"}\n- **coût** des **facteurs de production**\n\n^un produit intérieur brut // {\"headword\":\"produit intérieur brut\",\"category\":\"noun\",\"gender\":\"masculine\",\"cefrLevel\":\"B2\"}\n## Produit intérieur brut\n\n~? Produit Intérieur Brut :\n^mesurer // {\"headword\":\"mesure\",\"category\":\"noun\",\"gender\":\"feminine\",\"cefrLevel\":\"B1\"}\n^une valeur totale // {\"headword\":\"valeur totale\",\"category\":\"noun\",\"gender\":\"feminine\",\"cefrLevel\":\"B1\"}\n^un bien // {\"headword\":\"biens\",\"category\":\"noun\",\"gender\":\"masculine\",\"cefrLevel\":\"B1\"}\n^un service // {\"headword\":\"services\",\"category\":\"noun\",\"gender\":\"masculine\",\"cefrLevel\":\"A2\"}\n^final // {\"headword\":\"final\",\"category\":\"adjective\",\"cefrLevel\":\"B1\"}\n^produire // {\"headword\":\"produire\",\"category\":\"verb\",\"cefrLevel\":\"B1\"}\n^un pays // {\"headword\":\"pays\",\"category\":\"noun\",\"gender\":\"masculine\",\"cefrLevel\":\"A1\"}\n^une période // {\"headword\":\"période\",\"category\":\"noun\",\"gender\":\"feminine\",\"cefrLevel\":\"A2\"}\n**mesure** la **valeur totale** des **biens** et **services** **finaux** **produits** dans un pays sur une **période** donnée.\n\n^une formule // {\"headword\":\"formule\",\"category\":\"noun\",\"gender\":\"feminine\",\"cefrLevel\":\"B1\"}\n^calculer // {\"headword\":\"calculer\",\"category\":\"verb\",\"cefrLevel\":\"A1\"}\n?~ **Formule** pour calculer le **produit intérieur brut** à partir de la **production** :\n^une somme // {\"headword\":\"somme\",\"category\":\"noun\",\"gender\":\"feminine\",\"cefrLevel\":\"A2\"}\n- la **somme des valeurs ajoutées**\n^une TVA // {\"headword\":\"TVA\",\"category\":\"noun\",\"gender\":\"feminine\",\"cefrLevel\":\"B1\"}\n^plus // {\"headword\":\"plus\",\"category\":\"other\",\"cefrLevel\":\"A1\"}\n- **plus la TVA**\n^un droit de douane // {\"headword\":\"droit de douane\",\"category\":\"noun\",\"gender\":\"masculine\",\"cefrLevel\":\"B2\"}\n- **plus les droits de douane**\n^moins // {\"headword\":\"moins\",\"category\":\"other\",\"cefrLevel\":\"A1\"}\n^une subvention // {\"headword\":\"subvention\",\"category\":\"noun\",\"gender\":\"feminine\",\"cefrLevel\":\"B2\"}\n- **moins les subventions**.\n\n^une utilisation // {\"headword\":\"utilisation\",\"category\":\"noun\",\"gender\":\"feminine\",\"cefrLevel\":\"A2\"}\n?~ **Formule** pour calculer le **produit intérieur brut** à partir de l'**utilisation** des **biens** et **services** :\n^une consommation // {\"headword\":\"consommation\",\"category\":\"noun\",\"gender\":\"feminine\",\"cefrLevel\":\"B1\"}\n- consommation finale\n^une formation // {\"headword\":\"formation\",\"category\":\"noun\",\"gender\":\"feminine\",\"cefrLevel\":\"B1\"}\n^brut // {\"headword\":\"brut\",\"category\":\"adjective\",\"cefrLevel\":\"B1\"}\n^un capital // {\"headword\":\"capital\",\"category\":\"noun\",\"gender\":\"masculine\",\"cefrLevel\":\"B1\"}\n^fixe // {\"headword\":\"fixe\",\"category\":\"adjective\",\"cefrLevel\":\"A2\"}\n- **plus la formation brute de capital fixe**\n^courant // {\"headword\":\"courant\",\"category\":\"adjective\",\"cefrLevel\":\"A2\"}\n^une dépense publique // {\"headword\":\"dépense publique\",\"category\":\"noun\",\"gender\":\"feminine\",\"cefrLevel\":\"B2\"}\n- **plus les dépenses publiques courantes**\n^une variation // {\"headword\":\"variation\",\"category\":\"noun\",\"gender\":\"feminine\",\"cefrLevel\":\"B1\"}\n^un stock // {\"headword\":\"stock\",\"category\":\"noun\",\"gender\":\"masculine\",\"cefrLevel\":\"B1\"}\n- **plus la variation des stocks**\n^une exportation // {\"headword\":\"exportation\",\"category\":\"noun\",\"gender\":\"feminine\",\"cefrLevel\":\"B1\"}\n- **plus les exportations**\n^une importation // {\"headword\":\"importation\",\"category\":\"noun\",\"gender\":\"feminine\",\"cefrLevel\":\"B1\"}\n- **moins les importations**\n\n^un type // {\"headword\":\"type\",\"category\":\"noun\",\"gender\":\"masculine\",\"cefrLevel\":\"A2\"}\n?~ Types de PIB :\n^nominal // {\"headword\":\"nominal\",\"category\":\"other\",\"cefrLevel\":\"B2\"}\n- **nominal**\n^une inflation // {\"headword\":\"inflation\",\"category\":\"noun\",\"gender\":\"feminine\",\"cefrLevel\":\"B2\"}\n^réel // {\"headword\":\"réel\",\"category\":\"adjective\",\"cefrLevel\":\"B1\"}\n^corriger // {\"headword\":\"corriger\",\"category\":\"verb\",\"cefrLevel\":\"B1\"}\n^un prix // {\"headword\":\"prix\",\"category\":\"noun\",\"gender\":\"masculine\",\"cefrLevel\":\"A1\"}\n^une année de référence // {\"headword\":\"année de référence\",\"category\":\"noun\",\"gender\":\"feminine\",\"cefrLevel\":\"B2\"}\n- **réel**, **corrigé** de l'**inflation**, en le ramenant **aux prix d'une année de référence**.\n\n^un taux de change // {\"headword\":\"taux de change\",\"category\":\"noun\",\"gender\":\"masculine\",\"cefrLevel\":\"B1\"}\n^un pouvoir d'achat // {\"headword\":\"pouvoir d'achat\",\"category\":\"noun\",\"gender\":\"masculine\",\"cefrLevel\":\"B2\"}\n^une parité // {\"headword\":\"parité\",\"category\":\"noun\",\"cefrLevel\":\"C1\",\"gender\":\"feminine\"}\n~? Taux de change de parité de pouvoir d’achat :\n^comparer // {\"headword\":\"comparer\",\"category\":\"verb\",\"cefrLevel\":\"B1\"}\n^une quantité de monnaie // {\"headword\":\"quantité de monnaie\",\"category\":\"noun\",\"gender\":\"feminine\",\"cefrLevel\":\"A2\"}\n^d'un pays à l'autre // {\"headword\":\"d'un pays à l'autre\",\"category\":\"other\",\"cefrLevel\":\"B2\"}\npour **comparer** le **pouvoir d'achat** d'une **certaine quantité de monnaie** **d'un pays** **à** l'**autre**",
      "exported" : true,
      "llmTranslationLanguageSpecificInstructions" : null,
      "article" : null,
      "ttsMapping" : { },
      "sttMapping" : { },
      "tooltips" : { },
      "bibliographyUrls" : { }
    }, {
      "lang" : "EN",
      "title" : "Production aggregates",
      "description" : "...",
      "voice" : "en-US-Chirp3-HD-Fenrir",
      "text" : "^the aggregate // {\"headword\":\"aggregate\",\"category\":\"noun\",\"cefrLevel\":\"C1\"}\n^the production // {\"headword\":\"production\",\"category\":\"noun\",\"cefrLevel\":\"B2\"}\n# Production aggregates\n\n^the measure // {\"headword\":\"measure\",\"category\":\"noun\",\"cefrLevel\":\"B2\"}\n## Measuring production\n\n^market // {\"headword\":\"market\",\"category\":\"adjective\",\"cefrLevel\":\"B1\"}\n?~**Aggregate** measuring **market production**:\n^the value added // {\"headword\":\"value added\",\"category\":\"noun\",\"cefrLevel\":\"C1\"}\n^that is // {\"headword\":\"that is\",\"category\":\"other\",\"cefrLevel\":\"B1\"}\n- **value added**, that is:\n^the revenue // {\"headword\":\"turnover\",\"category\":\"noun\",\"cefrLevel\":\"B2\"}\n- **revenue**\n^minus // {\"headword\":\"minus\",\"category\":\"other\",\"cefrLevel\":\"B1\"}\n^the consumption // {\"headword\":\"consumption\",\"category\":\"noun\",\"cefrLevel\":\"B2\"}\n^intermediate // {\"headword\":\"intermediate\",\"category\":\"adjective\",\"cefrLevel\":\"B1\"}\n- **minus intermediate consumption**.\n\n^the estimation // {\"headword\":\"estimation\",\"category\":\"noun\",\"cefrLevel\":\"B2\"}\n^non-market // {\"headword\":\"non-market\",\"category\":\"adjective\",\"cefrLevel\":\"C1\"}\n?~**Estimation** of **non-market production**:\n^the cost // {\"headword\":\"cost\",\"category\":\"noun\",\"cefrLevel\":\"A2\"}\n^the factor of production // {\"headword\":\"factor of production\",\"category\":\"noun\",\"cefrLevel\":\"C1\"}\n- **cost** of the **factors of production**\n\n^the gross domestic product // {\"headword\":\"gross domestic product\",\"category\":\"noun\",\"cefrLevel\":\"C1\"}\n## Gross domestic product\n\n~?Gross Domestic Product:\n^to measure // {\"headword\":\"measures\",\"category\":\"noun\",\"cefrLevel\":\"B2\"}\n^the total value // {\"headword\":\"total value\",\"category\":\"noun\",\"cefrLevel\":\"B2\"}\n^the good // {\"headword\":\"goods\",\"category\":\"noun\",\"cefrLevel\":\"B2\"}\n^the service // {\"headword\":\"services\",\"category\":\"noun\",\"cefrLevel\":\"B1\"}\n^final // {\"headword\":\"final\",\"category\":\"adjective\",\"cefrLevel\":\"B1\"}\n^produce // {\"headword\":\"produce\",\"category\":\"verb\",\"cefrLevel\":\"B1\"}\n^the country // {\"headword\":\"country\",\"category\":\"noun\",\"cefrLevel\":\"A1\"}\n^the period // {\"headword\":\"period\",\"category\":\"noun\",\"cefrLevel\":\"B1\"}\n**measures** the **total value** of **final** **goods** and **services** **produced** in a country over a given **period**.\n\n^the formula // {\"headword\":\"formula\",\"category\":\"noun\",\"cefrLevel\":\"B2\"}\n^calculate // {\"headword\":\"calculate\",\"category\":\"verb\",\"cefrLevel\":\"B1\"}\n?~**Formula** to calculate **gross domestic product** from **production**:\n^the sum // {\"headword\":\"sum\",\"category\":\"noun\",\"cefrLevel\":\"B1\"}\n- the **sum of value added**\n^the VAT // {\"headword\":\"VAT\",\"category\":\"noun\",\"cefrLevel\":\"B2\"}\n^plus // {\"headword\":\"plus\",\"category\":\"other\",\"cefrLevel\":\"A2\"}\n- **plus VAT**\n^the custom duty // {\"headword\":\"custom duty\",\"category\":\"noun\",\"cefrLevel\":\"B2\"}\n- **plus customs duties**\n^minus // {\"headword\":\"minus\",\"category\":\"other\",\"cefrLevel\":\"B2\"}\n^the subsidy // {\"headword\":\"subsidy\",\"category\":\"noun\",\"cefrLevel\":\"C1\"}\n- **minus subsidies**.\n\n^the use // {\"headword\":\"use\",\"category\":\"noun\",\"cefrLevel\":\"A2\"}\n?~**Formula** to calculate **gross domestic product** from the **use** of **goods** and **services**:\n^the consumption // {\"headword\":\"consumption\",\"category\":\"noun\",\"cefrLevel\":\"B2\"}\n- final consumption\n^the formation // {\"headword\":\"formation\",\"category\":\"noun\",\"cefrLevel\":\"B2\"}\n^gross // {\"headword\":\"gross\",\"category\":\"adjective\",\"cefrLevel\":\"B2\"}\n^the capital // {\"headword\":\"capital\",\"category\":\"noun\",\"cefrLevel\":\"B2\"}\n^fixed // {\"headword\":\"fixed\",\"category\":\"adjective\",\"cefrLevel\":\"B1\"}\n- **plus gross fixed capital formation**\n^current // {\"headword\":\"current\",\"category\":\"adjective\",\"cefrLevel\":\"B1\"}\n^the public expenditure // {\"headword\":\"public expenditure\",\"category\":\"noun\",\"cefrLevel\":\"C1\"}\n- **plus current public expenditure**\n^the change // {\"headword\":\"change\",\"category\":\"noun\",\"cefrLevel\":\"A2\"}\n^the inventory // {\"headword\":\"inventory\",\"category\":\"noun\",\"cefrLevel\":\"B2\"}\n- **plus change in inventories**\n^the export // {\"headword\":\"export\",\"category\":\"noun\",\"cefrLevel\":\"B2\"}\n- **plus exports**\n^the import // {\"headword\":\"import\",\"category\":\"noun\",\"cefrLevel\":\"B2\"}\n- **minus imports**\n\n^the type // {\"headword\":\"type\",\"category\":\"noun\",\"cefrLevel\":\"A2\"}\n?~Types of GDP:\n^nominal // {\"headword\":\"nominal\",\"category\":\"other\",\"cefrLevel\":\"C1\"}\n- **nominal**\n^the inflation // {\"headword\":\"inflation\",\"category\":\"noun\",\"cefrLevel\":\"B2\"}\n^real // {\"headword\":\"real\",\"category\":\"adjective\",\"cefrLevel\":\"A1\"}\n^adjust // {\"headword\":\"adjust\",\"category\":\"verb\",\"cefrLevel\":\"B1\"}\n^the price // {\"headword\":\"price\",\"category\":\"noun\",\"cefrLevel\":\"A2\"}\n^the reference year // {\"headword\":\"reference year\",\"category\":\"noun\",\"cefrLevel\":\"B2\"}\n- **real**, **adjusted** for **inflation**, by expressing it **at the prices of a reference year**.\n\n^the exchange rate // {\"headword\":\"exchange rate\",\"category\":\"noun\",\"cefrLevel\":\"B2\"}\n^the purchasing power // {\"headword\":\"purchasing power\",\"category\":\"noun\",\"cefrLevel\":\"B2\"}\n^parity // {\"headword\":\"parity\",\"category\":\"adjective\",\"cefrLevel\":\"C1\"}\n~?Purchasing power parity exchange rate:\n^compare // {\"headword\":\"compare\",\"category\":\"verb\",\"cefrLevel\":\"A2\"}\n^the amount of money // {\"headword\":\"amount of money\",\"category\":\"noun\",\"cefrLevel\":\"B1\"}\n^from one country to another // {\"headword\":\"from one country to another\",\"category\":\"other\",\"cefrLevel\":\"B1\"}\nto **compare** the **purchasing power** of a **given amount of money** **from one country** **to** **another**",
      "exported" : true,
      "llmTranslationLanguageSpecificInstructions" : null,
      "article" : null,
      "ttsMapping" : { },
      "sttMapping" : { },
      "tooltips" : { },
      "bibliographyUrls" : { }
    }, {
      "lang" : "DE",
      "title" : "Produktionsaggregate",
      "description" : "...",
      "voice" : "de-DE-Chirp3-HD-Fenrir",
      "text" : "^das Aggregat // {\"headword\":\"Aggregat\",\"category\":\"noun\",\"gender\":\"neuter\",\"cefrLevel\":\"B2\"}\n^die Produktion // {\"headword\":\"Produktion\",\"category\":\"noun\",\"gender\":\"feminine\",\"cefrLevel\":\"B1\"}\n# Produktionsaggregate\n\n^die Messung // {\"headword\":\"Messung\",\"category\":\"noun\",\"gender\":\"feminine\",\"cefrLevel\":\"B1\"}\n## Messung der Produktion\n\n^marktwirtschaftlich // {\"headword\":\"marktwirtschaftlich\",\"category\":\"adjective\",\"cefrLevel\":\"C1\"}\n?~**Aggregat** zur Messung der **marktwirtschaftlichen Produktion**:\n^die Wertschöpfung // {\"headword\":\"Wertschöpfung\",\"category\":\"noun\",\"gender\":\"feminine\",\"cefrLevel\":\"C1\"}\n^das heißt // {\"headword\":\"das heißt\",\"category\":\"other\",\"cefrLevel\":\"A2\"}\n- die **Wertschöpfung**, das heißt:\n^der Umsatz // {\"headword\":\"Umsatz\",\"category\":\"noun\",\"gender\":\"masculine\",\"cefrLevel\":\"B2\"}\n- der **Umsatz**\n^minus // {\"headword\":\"minus\",\"category\":\"other\",\"cefrLevel\":\"B1\"}\n^der Verbrauch // {\"headword\":\"Verbrauch\",\"category\":\"noun\",\"gender\":\"masculine\",\"cefrLevel\":\"B1\"}\n^vorleistungs // {\"headword\":\"vorleistungs\",\"category\":\"adjective\",\"cefrLevel\":\"C1\"}\n- **minus der Vorleistungsverbrauch**.\n\n^die Schätzung // {\"headword\":\"Schätzung\",\"category\":\"noun\",\"gender\":\"feminine\",\"cefrLevel\":\"B1\"}\n^nichtmarktwirtschaftlich // {\"headword\":\"nichtmarktwirtschaftlichen\",\"category\":\"adjective\",\"cefrLevel\":\"C1\"}\n?~**Schätzung** der **nichtmarktwirtschaftlichen Produktion**:\n^die Kosten // {\"headword\":\"Kosten\",\"category\":\"noun\",\"gender\":\"plural\",\"cefrLevel\":\"A2\"}\n^der Produktionsfaktor // {\"headword\":\"Produktionsfaktor\",\"category\":\"noun\",\"gender\":\"masculine\",\"cefrLevel\":\"B2\"}\n- **Kosten** der **Produktionsfaktoren**\n\n^das Bruttoinlandsprodukt // {\"headword\":\"Bruttoinlandsprodukt\",\"category\":\"noun\",\"gender\":\"neuter\",\"cefrLevel\":\"B2\"}\n## Bruttoinlandsprodukt\n\n~?Bruttoinlandsprodukt:\n^messen // {\"headword\":\"Misst\",\"category\":\"noun\",\"gender\":\"masculine\",\"cefrLevel\":\"B2\"}\n^der Gesamtwert // {\"headword\":\"Gesamtwert\",\"category\":\"noun\",\"gender\":\"masculine\",\"cefrLevel\":\"B2\"}\n^das Gut // {\"headword\":\"Güter\",\"category\":\"noun\",\"gender\":\"neuter\",\"cefrLevel\":\"B1\"}\n^die Dienstleistung // {\"headword\":\"Dienstleistungen\",\"category\":\"noun\",\"gender\":\"feminine\",\"cefrLevel\":\"B1\"}\n^endgültig // {\"headword\":\"endgültigen\",\"category\":\"adjective\",\"cefrLevel\":\"B2\"}\n^produzieren // {\"headword\":\"produzieren\",\"category\":\"verb\",\"cefrLevel\":\"B1\"}\n^das Land // {\"headword\":\"Land\",\"category\":\"noun\",\"gender\":\"neuter\",\"cefrLevel\":\"A1\"}\n^der Zeitraum // {\"headword\":\"Zeitraum\",\"category\":\"noun\",\"gender\":\"masculine\",\"cefrLevel\":\"B1\"}\n**misst** den **Gesamtwert** der **endgültigen Güter** und **Dienstleistungen**, die in einem Land in einem bestimmten **Zeitraum** **produziert** werden.\n\n^die Formel // {\"headword\":\"Formel\",\"category\":\"noun\",\"gender\":\"feminine\",\"cefrLevel\":\"B1\"}\n^berechnen // {\"headword\":\"berechnen\",\"category\":\"verb\",\"cefrLevel\":\"B1\"}\n?~**Formel** zur Berechnung des **Bruttoinlandsprodukts** ausgehend von der **Produktion**:\n^die Summe // {\"headword\":\"Summe\",\"category\":\"noun\",\"gender\":\"feminine\",\"cefrLevel\":\"A2\"}\n- die **Summe der Wertschöpfungen**\n^die Mehrwertsteuer // {\"headword\":\"Mehrwertsteuer\",\"category\":\"noun\",\"gender\":\"feminine\",\"cefrLevel\":\"B1\"}\n^plus // {\"headword\":\"plus\",\"category\":\"other\",\"cefrLevel\":\"A2\"}\n- **plus die Mehrwertsteuer**\n^der Zoll // {\"headword\":\"Zoll\",\"category\":\"noun\",\"gender\":\"masculine\",\"cefrLevel\":\"B1\"}\n- **plus die Zölle**\n^minus // {\"headword\":\"minus\",\"category\":\"other\",\"cefrLevel\":\"B1\"}\n^die Subvention // {\"headword\":\"Subvention\",\"category\":\"noun\",\"gender\":\"feminine\",\"cefrLevel\":\"B2\"}\n- **minus die Subventionen**.\n\n^die Verwendung // {\"headword\":\"Verwendung\",\"category\":\"noun\",\"gender\":\"feminine\",\"cefrLevel\":\"B1\"}\n?~**Formel** zur Berechnung des **Bruttoinlandsprodukts** ausgehend von der **Verwendung** der **Güter** und **Dienstleistungen**:\n^der Verbrauch // {\"headword\":\"Verbrauch\",\"category\":\"noun\",\"gender\":\"masculine\",\"cefrLevel\":\"B1\"}\n- Endverbrauch\n^die Anlageinvestition // {\"headword\":\"Anlageinvestition\",\"category\":\"noun\",\"gender\":\"feminine\",\"cefrLevel\":\"C1\"}\n^Brutto // {\"headword\":\"Brutto\",\"category\":\"adjective\",\"cefrLevel\":\"B1\"}\n^das Kapital // {\"headword\":\"Kapital\",\"category\":\"noun\",\"gender\":\"neuter\",\"cefrLevel\":\"B1\"}\n^Anlage // {\"headword\":\"Anlage\",\"category\":\"other\",\"cefrLevel\":\"B2\"}\n- **plus die Bruttoanlageinvestitionen**\n^laufend // {\"headword\":\"laufend\",\"category\":\"adjective\",\"cefrLevel\":\"B1\"}\n^die Staatsausgabe // {\"headword\":\"Staatsausgabe\",\"category\":\"noun\",\"gender\":\"feminine\",\"cefrLevel\":\"B2\"}\n- **plus die laufenden Staatsausgaben**\n^die Veränderung // {\"headword\":\"Veränderung\",\"category\":\"noun\",\"gender\":\"feminine\",\"cefrLevel\":\"B1\"}\n^der Lagerbestand // {\"headword\":\"Lagerbestand\",\"category\":\"noun\",\"gender\":\"masculine\",\"cefrLevel\":\"B2\"}\n- **plus die Veränderung der Lagerbestände**\n^der Export // {\"headword\":\"Export\",\"category\":\"noun\",\"gender\":\"masculine\",\"cefrLevel\":\"B1\"}\n- **plus die Exporte**\n^der Import // {\"headword\":\"Import\",\"category\":\"noun\",\"gender\":\"masculine\",\"cefrLevel\":\"B2\"}\n- **minus die Importe**\n\n^die Art // {\"headword\":\"Art\",\"category\":\"noun\",\"gender\":\"feminine\",\"cefrLevel\":\"B1\"}\n?~Arten des BIP:\n^nominal // {\"headword\":\"nominal\",\"category\":\"other\",\"cefrLevel\":\"B2\"}\n- **nominal**\n^die Inflation // {\"headword\":\"Inflation\",\"category\":\"noun\",\"gender\":\"feminine\",\"cefrLevel\":\"B2\"}\n^real // {\"headword\":\"real\",\"category\":\"adjective\",\"cefrLevel\":\"B1\"}\n^bereinigen // {\"headword\":\"bereinigen\",\"category\":\"verb\",\"cefrLevel\":\"C1\"}\n^der Preis // {\"headword\":\"Preis\",\"category\":\"noun\",\"gender\":\"masculine\",\"cefrLevel\":\"A1\"}\n^das Basisjahr // {\"headword\":\"Basisjahr\",\"category\":\"noun\",\"gender\":\"neuter\",\"cefrLevel\":\"B2\"}\n- **real**, **bereinigt** um die **Inflation**, indem man es **auf die Preise eines Basisjahres** bezieht.\n\n^der Wechselkurs // {\"headword\":\"Wechselkurs\",\"category\":\"noun\",\"gender\":\"masculine\",\"cefrLevel\":\"B2\"}\n^die Kaufkraft // {\"headword\":\"Kaufkraft\",\"category\":\"noun\",\"gender\":\"feminine\",\"cefrLevel\":\"B2\"}\n^Parität // {\"headword\":\"Parität\",\"category\":\"adjective\",\"cefrLevel\":\"C1\"}\n~?Kaufkraftparitätenwechselkurs:\n^vergleichen // {\"headword\":\"vergleichen\",\"category\":\"verb\",\"cefrLevel\":\"B1\"}\n^die Geldmenge // {\"headword\":\"Geldmenge\",\"category\":\"noun\",\"gender\":\"feminine\",\"cefrLevel\":\"B2\"}\n^eines Landes mit der eines anderen // {\"headword\":\"eines Landes mit der eines anderen\",\"category\":\"other\",\"cefrLevel\":\"B2\"}\num die **Kaufkraft** einer **bestimmten Geldmenge** **eines Landes** **mit** der **eines anderen** **zu vergleichen**",
      "exported" : true,
      "llmTranslationLanguageSpecificInstructions" : null,
      "article" : null,
      "ttsMapping" : { },
      "sttMapping" : { },
      "tooltips" : { },
      "bibliographyUrls" : { }
    }, {
      "lang" : "ZH",
      "title" : "生产总量",
      "description" : "...",
      "voice" : "cmn-CN-Chirp3-HD-Fenrir",
      "text" : "^一个总量 // {\"headword\":\"总量\",\"category\":\"noun\",\"classifier\":\"个\",\"pinyin\":\"zǒng liàng\",\"cefrLevel\":\"B2\"}\n^一个生产 // {\"headword\":\"生产\",\"category\":\"noun\",\"classifier\":\"个\",\"pinyin\":\"shēng chǎn\",\"cefrLevel\":\"B1\"}\n# 生产总量\n\n^一个衡量 // {\"headword\":\"衡量\",\"category\":\"noun\",\"classifier\":\"个\",\"pinyin\":\"héng liáng\",\"cefrLevel\":\"B2\"}\n## 生产衡量\n\n^商品 // {\"headword\":\"商品\",\"category\":\"noun\",\"pinyin\":\"shāng pǐn\",\"cefrLevel\":\"A2\",\"classifier\":\"件\"}\n?~衡量**商品生产**的**总量指标**：\n^一个增加值 // {\"headword\":\"增加值\",\"category\":\"noun\",\"classifier\":\"个\",\"pinyin\":\"zēng jiā zhí\",\"cefrLevel\":\"B2\"}\n^即 // {\"headword\":\"即\",\"category\":\"other\",\"cefrLevel\":\"B2\",\"pinyin\":\"jí\"}\n- **增加值**，即：\n^一笔营业收入 // {\"headword\":\"营业收入\",\"category\":\"noun\",\"classifier\":\"笔\",\"pinyin\":\"yíng yè shōu rù\",\"cefrLevel\":\"B2\"}\n- **营业收入**\n^减去 // {\"headword\":\"减去\",\"category\":\"other\",\"cefrLevel\":\"B1\",\"pinyin\":\"jiǎn qù\"}\n^一种消耗 // {\"headword\":\"消耗\",\"category\":\"noun\",\"classifier\":\"种\",\"pinyin\":\"xiāo hào\",\"cefrLevel\":\"B2\"}\n^中间 // {\"headword\":\"中间\",\"category\":\"adjective\",\"pinyin\":\"zhōng jiān\",\"cefrLevel\":\"A1\"}\n- **减去中间消耗**\n\n^一个估算方法 // {\"headword\":\"估算方法\",\"category\":\"noun\",\"classifier\":\"个\",\"pinyin\":\"gū suàn fāng fǎ\",\"cefrLevel\":\"B2\"}\n^非商品 // {\"headword\":\"非商品\",\"category\":\"adjective\",\"pinyin\":\"fēi shāng pǐn\",\"cefrLevel\":\"B2\"}\n?~**非商品生产**的**估算方法**：\n^一个成本 // {\"headword\":\"成本\",\"category\":\"noun\",\"classifier\":\"个\",\"pinyin\":\"chéng běn\",\"cefrLevel\":\"B1\"}\n^一种生产要素 // {\"headword\":\"生产要素\",\"category\":\"noun\",\"classifier\":\"种\",\"pinyin\":\"shēng chǎn yào sù\",\"cefrLevel\":\"B2\"}\n- **生产要素**的**成本**\n\n^一个国内生产总值 // {\"headword\":\"国内生产总值\",\"category\":\"noun\",\"classifier\":\"个\",\"pinyin\":\"guó nèi shēng chǎn zǒng zhí\",\"cefrLevel\":\"C1\"}\n## 国内生产总值\n\n~?国内生产总值：\n^衡量 // {\"headword\":\"衡量\",\"category\":\"noun\",\"classifier\":\"个\",\"pinyin\":\"héng liáng\",\"cefrLevel\":\"B2\"}\n^一个总值 // {\"headword\":\"总值\",\"category\":\"noun\",\"classifier\":\"个\",\"pinyin\":\"zǒng zhí\",\"cefrLevel\":\"B2\"}\n^一个商品 // {\"headword\":\"商品\",\"category\":\"noun\",\"classifier\":\"个\",\"pinyin\":\"shāng pǐn\",\"cefrLevel\":\"B1\"}\n^一项服务 // {\"headword\":\"服务\",\"category\":\"noun\",\"classifier\":\"项\",\"pinyin\":\"fú wù\",\"cefrLevel\":\"B1\"}\n^最终 // {\"headword\":\"最终\",\"category\":\"adjective\",\"pinyin\":\"zuì zhōng\",\"cefrLevel\":\"B1\"}\n^生产 // {\"headword\":\"生产\",\"category\":\"verb\",\"pinyin\":\"shēng chǎn\",\"cefrLevel\":\"B1\"}\n^一个国家 // {\"headword\":\"国家\",\"category\":\"noun\",\"classifier\":\"个\",\"pinyin\":\"guó jiā\",\"cefrLevel\":\"A2\"}\n^一个期间 // {\"headword\":\"期间\",\"category\":\"noun\",\"classifier\":\"个\",\"pinyin\":\"qī jiān\",\"cefrLevel\":\"B1\"}\n**衡量**一个国家在特定**期间内**所**生产**的最终**商品**与**服务**的**总值**。\n\n^一个公式 // {\"headword\":\"公式\",\"category\":\"noun\",\"classifier\":\"个\",\"pinyin\":\"gōng shì\",\"cefrLevel\":\"B1\"}\n^计算 // {\"headword\":\"计算\",\"category\":\"verb\",\"pinyin\":\"jì suàn\",\"cefrLevel\":\"A2\"}\n?~从**生产**角度计算**国内生产总值**的**公式**：\n^一个总和 // {\"headword\":\"总和\",\"category\":\"noun\",\"classifier\":\"个\",\"pinyin\":\"zǒng hé\",\"cefrLevel\":\"B2\"}\n- **增加值总和**\n^一种增值税 // {\"headword\":\"增值税\",\"category\":\"noun\",\"classifier\":\"种\",\"pinyin\":\"zēng zhí shuì\",\"cefrLevel\":\"C1\"}\n^加 // {\"headword\":\"加\",\"category\":\"other\",\"cefrLevel\":\"A1\",\"pinyin\":\"jiā\"}\n- **加增值税**\n^一种关税 // {\"headword\":\"关税\",\"category\":\"noun\",\"classifier\":\"种\",\"pinyin\":\"guān shuì\",\"cefrLevel\":\"B2\"}\n- **加关税**\n^减 // {\"headword\":\"减\",\"category\":\"other\",\"cefrLevel\":\"A2\",\"pinyin\":\"jiǎn\"}\n^一项补贴 // {\"headword\":\"补贴\",\"category\":\"noun\",\"classifier\":\"项\",\"pinyin\":\"bǔ tiē\",\"cefrLevel\":\"B2\"}\n- **减补贴**\n\n^一种使用 // {\"headword\":\"使用\",\"category\":\"noun\",\"classifier\":\"种\",\"pinyin\":\"shǐ yòng\",\"cefrLevel\":\"B1\"}\n?~从**商品**与**服务**的**使用**角度计算**国内生产总值**的**公式**：\n^一种消费 // {\"headword\":\"消费\",\"category\":\"noun\",\"classifier\":\"种\",\"pinyin\":\"xiāo fèi\",\"cefrLevel\":\"B1\"}\n- 最终消费\n^一个形成 // {\"headword\":\"形成\",\"category\":\"noun\",\"classifier\":\"个\",\"pinyin\":\"xíng chéng\",\"cefrLevel\":\"B1\"}\n^总额 // {\"headword\":\"总额\",\"category\":\"adjective\",\"pinyin\":\"zǒng é\",\"cefrLevel\":\"B2\"}\n^一笔资本 // {\"headword\":\"资本\",\"category\":\"noun\",\"classifier\":\"笔\",\"pinyin\":\"zī běn\",\"cefrLevel\":\"B2\"}\n^固定 // {\"headword\":\"固定\",\"category\":\"adjective\",\"pinyin\":\"gù dìng\",\"cefrLevel\":\"B1\"}\n- **加固定资产本形成总额**\n^经常性 // {\"headword\":\"经常性\",\"category\":\"adjective\",\"pinyin\":\"jīng cháng xìng\",\"cefrLevel\":\"B2\"}\n^一项公共支出 // {\"headword\":\"公共支出\",\"category\":\"noun\",\"classifier\":\"项\",\"pinyin\":\"gōng gòng zhī chū\",\"cefrLevel\":\"B2\"}\n- **加经常性公共支出**\n^一个变动 // {\"headword\":\"变动\",\"category\":\"noun\",\"classifier\":\"个\",\"pinyin\":\"biàn dòng\",\"cefrLevel\":\"B2\"}\n^一批存货 // {\"headword\":\"存货\",\"category\":\"noun\",\"classifier\":\"批\",\"pinyin\":\"cún huò\",\"cefrLevel\":\"B2\"}\n- **加存货变动**\n^一个出口额 // {\"headword\":\"出口额\",\"category\":\"noun\",\"classifier\":\"个\",\"pinyin\":\"chū kǒu é\",\"cefrLevel\":\"B2\"}\n- **加出口额**\n^一个进口额 // {\"headword\":\"进口额\",\"category\":\"noun\",\"classifier\":\"个\",\"pinyin\":\"jìn kǒu é\",\"cefrLevel\":\"B2\"}\n- **减进口额**\n\n^一个类型 // {\"headword\":\"类型\",\"category\":\"noun\",\"classifier\":\"个\",\"pinyin\":\"lèi xíng\",\"cefrLevel\":\"B1\"}\n?~GDP类型：\n^名义 // {\"headword\":\"名义\",\"category\":\"other\",\"cefrLevel\":\"B2\",\"pinyin\":\"míng yì\"}\n- **名义**\n^一种通胀 // {\"headword\":\"通胀\",\"category\":\"noun\",\"classifier\":\"种\",\"pinyin\":\"tōng zhàng\",\"cefrLevel\":\"B2\"}\n^实际 // {\"headword\":\"实际\",\"category\":\"adjective\",\"pinyin\":\"shí jì\",\"cefrLevel\":\"B1\"}\n^调整 // {\"headword\":\"调整\",\"category\":\"verb\",\"pinyin\":\"tiáo zhěng\",\"cefrLevel\":\"B1\"}\n^一个价格 // {\"headword\":\"价格\",\"category\":\"noun\",\"classifier\":\"个\",\"pinyin\":\"jià gé\",\"cefrLevel\":\"B1\"}\n^一个基准年份 // {\"headword\":\"基准年份\",\"category\":\"noun\",\"classifier\":\"个\",\"pinyin\":\"jī zhǔn nián fèn\",\"cefrLevel\":\"B2\"}\n- **实际**（经**通胀**调整后，**按基准年份价格**计算）\n\n^一个汇率 // {\"headword\":\"汇率\",\"category\":\"noun\",\"classifier\":\"个\",\"pinyin\":\"huì lǜ\",\"cefrLevel\":\"B2\"}\n^一种购买力 // {\"headword\":\"购买力\",\"category\":\"noun\",\"classifier\":\"种\",\"pinyin\":\"gòu mǎi lì\",\"cefrLevel\":\"B2\"}\n^平价 // {\"headword\":\"平价\",\"category\":\"adjective\",\"pinyin\":\"píng jià\",\"cefrLevel\":\"B1\"}\n~?购买力平价汇率：\n^比较 // {\"headword\":\"比较\",\"category\":\"verb\",\"pinyin\":\"bǐ jiào\",\"cefrLevel\":\"A2\"}\n^一种金额货币 // {\"headword\":\"金额货币\",\"category\":\"noun\",\"classifier\":\"种\",\"pinyin\":\"jīn é huò bì\",\"cefrLevel\":\"B2\"}\n^不同国家 // {\"headword\":\"不同国家\",\"category\":\"other\",\"cefrLevel\":\"A2\",\"pinyin\":\"bù tóng guó jiā\"}\n用于**比较**「**特定金额货币**」在「**不同国家**」的**购买力**",
      "exported" : true,
      "llmTranslationLanguageSpecificInstructions" : null,
      "article" : null,
      "ttsMapping" : { },
      "sttMapping" : { },
      "tooltips" : { },
      "bibliographyUrls" : { }
    } ],
    "modificationDate" : "2025-08-18T16:05:42.613846383Z",
    "quality" : "LOW"
  }
}